.bumpversion.cfg
.gitignore
CMakeLists.txt
LICENSE
README.md
README.rst
pyproject.toml
setup.py
.github/ISSUE_TEMPLATE.md
.github/workflows/publish.yml
cmake/CodeCoverage.cmake
cmake/cmake_uninstall.cmake.in
pylc3.core.egg-info/PKG-INFO
pylc3.core.egg-info/SOURCES.txt
pylc3.core.egg-info/dependency_links.txt
pylc3.core.egg-info/not-zip-safe
pylc3.core.egg-info/top_level.txt
pylc3/core/PyLC3.cpp
pylc3/core/PyLC3.hpp
pylc3/core/__init__.py
scripts/pylc3_generator.py