Metadata-Version: 2.1
Name: pylc3.core
Version: 0.1.6
Summary: Python bindings for liblc3, the LC-3 simulator framework
Home-page: https://github.com/complx-tools/pylc3.core
Author: Brandon Whitehead
Author-email: brandon.whitehead@gatech.edu
License: GNU General Public License v3
License-File: LICENSE
